zksync_sdk/__init__.py
zksync_sdk/contract_utils.py
zksync_sdk/ethereum_provider.py
zksync_sdk/lib.py
zksync_sdk/network.py
zksync_sdk/py.typed
zksync_sdk/serializers.py
zksync_sdk/wallet.py
zksync_sdk/zksync.py
zksync_sdk/zksync_signer.py
zksync_sdk/contract_abi/IERC20.json
zksync_sdk/contract_abi/ZkSync.json
zksync_sdk/contract_abi/__init__.py
zksync_sdk/ethereum_signer/__init__.py
zksync_sdk/ethereum_signer/interface.py
zksync_sdk/ethereum_signer/web3.py
zksync_sdk/transport/__init__.py
zksync_sdk/transport/http.py
zksync_sdk/types/__init__.py
zksync_sdk/types/auth_types.py
zksync_sdk/types/responses.py
zksync_sdk/types/signatures.py
zksync_sdk/types/transactions.py
zksync_sdk/zksync_provider/__init__.py
zksync_sdk/zksync_provider/batch_builder.py
zksync_sdk/zksync_provider/error.py
zksync_sdk/zksync_provider/interface.py
zksync_sdk/zksync_provider/transaction.py
zksync_sdk/zksync_provider/types.py
zksync_sdk/zksync_provider/v01.py
zksync_sdk-0.1.667.dist-info/LICENSE
zksync_sdk-0.1.667.dist-info/METADATA
zksync_sdk-0.1.667.dist-info/WHEEL
zksync_sdk-0.1.667.dist-info/top_level.txt
zksync_sdk-0.1.667.dist-info/RECORD
